PytorchShenduXuexiShiyongZhinanChuyiFix1/README.md
PytorchShenduXuexiShiyongZhinanChuyiFix1/__init__.py
PytorchShenduXuexiShiyongZhinanChuyiFix1/__main__.py
PytorchShenduXuexiShiyongZhinanChuyiFix1/file.epub
PytorchShenduXuexiShiyongZhinanChuyiFix1/index.html
PytorchShenduXuexiShiyongZhinanChuyiFix1/css/__init__.py
PytorchShenduXuexiShiyongZhinanChuyiFix1/css/annotations.css
PytorchShenduXuexiShiyongZhinanChuyiFix1/css/main.css
PytorchShenduXuexiShiyongZhinanChuyiFix1/css/normalize.css
PytorchShenduXuexiShiyongZhinanChuyiFix1/css/popup.css
PytorchShenduXuexiShiyongZhinanChuyiFix1/font/__init__.py
PytorchShenduXuexiShiyongZhinanChuyiFix1/font/fontello.eot
PytorchShenduXuexiShiyongZhinanChuyiFix1/font/fontello.svg
PytorchShenduXuexiShiyongZhinanChuyiFix1/font/fontello.ttf
PytorchShenduXuexiShiyongZhinanChuyiFix1/font/fontello.woff
PytorchShenduXuexiShiyongZhinanChuyiFix1/img/__init__.py
PytorchShenduXuexiShiyongZhinanChuyiFix1/img/annotator-glyph-sprite.png
PytorchShenduXuexiShiyongZhinanChuyiFix1/img/annotator-icon-sprite.png
PytorchShenduXuexiShiyongZhinanChuyiFix1/img/apple-touch-icon.png
PytorchShenduXuexiShiyongZhinanChuyiFix1/img/cancelfullscreen.png
PytorchShenduXuexiShiyongZhinanChuyiFix1/img/close.png
PytorchShenduXuexiShiyongZhinanChuyiFix1/img/fullscreen.png
PytorchShenduXuexiShiyongZhinanChuyiFix1/img/loader.gif
PytorchShenduXuexiShiyongZhinanChuyiFix1/img/menu-icon.png
PytorchShenduXuexiShiyongZhinanChuyiFix1/img/save.png
PytorchShenduXuexiShiyongZhinanChuyiFix1/img/saved.png
PytorchShenduXuexiShiyongZhinanChuyiFix1/img/settings-s.png
PytorchShenduXuexiShiyongZhinanChuyiFix1/img/settings.png
PytorchShenduXuexiShiyongZhinanChuyiFix1/img/star.png
PytorchShenduXuexiShiyongZhinanChuyiFix1/js/__init__.py
PytorchShenduXuexiShiyongZhinanChuyiFix1/js/epub.js
PytorchShenduXuexiShiyongZhinanChuyiFix1/js/epub.min.js
PytorchShenduXuexiShiyongZhinanChuyiFix1/js/epub.min.map
PytorchShenduXuexiShiyongZhinanChuyiFix1/js/hooks.min.js
pytorch_shendu_xuexi_shiyong_zhinan_chuyi_fix1-2025.3.25.0.dist-info/METADATA
pytorch_shendu_xuexi_shiyong_zhinan_chuyi_fix1-2025.3.25.0.dist-info/WHEEL
pytorch_shendu_xuexi_shiyong_zhinan_chuyi_fix1-2025.3.25.0.dist-info/entry_points.txt
pytorch_shendu_xuexi_shiyong_zhinan_chuyi_fix1-2025.3.25.0.dist-info/top_level.txt
pytorch_shendu_xuexi_shiyong_zhinan_chuyi_fix1-2025.3.25.0.dist-info/RECORD
